i2crelay-0.1.0.dist-info/top_level.txt
i2crelay-0.1.0.dist-info/DESCRIPTION.rst
i2crelay-0.1.0.dist-info/entry_points.txt
i2crelay-0.1.0.dist-info/WHEEL
i2crelay-0.1.0.dist-info/METADATA
i2crelay-0.1.0.dist-info/RECORD
i2crelay-0.1.0.dist-info/metadata.json
i2crelay/__init__.py
i2crelay/i2crelay.py
i2crelay/cmdlinetool/__init__.py
