Metadata-Version: 2.0
Name: i2crelay
Version: 0.1.0
Summary: A library and command line tool to control PCF8574 I2C relay boards
Home-page: https://github.com/oweidner/i2crelay
Author: Ole Weidner, Codewerft UG (haftungsbeschraenkt)
Author-email: ole.weidner@codewerft.net
License: GPL-2.0
Keywords: relay i2c pcf8574 raspberry automation
Platform: UNKNOWN
Classifier: Development Status :: 3 - Alpha
Classifier: Intended Audience :: Developers
Classifier: Topic :: Software Development :: Build Tools
Classifier: License :: OSI Approved :: MIT License
Classifier: Programming Language :: Python :: 2
Classifier: Programming Language :: Python :: 2.7
Classifier: Programming Language :: Python :: 3
Classifier: Programming Language :: Python :: 3.3
Classifier: Programming Language :: Python :: 3.4
Classifier: Programming Language :: Python :: 3.5
Requires-Dist: smbus2
Requires-Dist: click
Provides-Extra: dev
Requires-Dist: check-manifest; extra == 'dev'
Provides-Extra: test
Requires-Dist: coverage; extra == 'test'
